pybacen/__init__.py
pybacen/bacen/__init__.py
pybacen/bacen/open_data.py
pybacen/bacen/time_series.py
pybacen/cvm/__init__.py
pybacen/cvm/investment_funds.py
pybacen/tests/__init__.py
pybacen/tests/test_pytest.py
pybacen/utils/__init__.py
pybacen/utils/requests.py
pybacen/utils/validators.py
pybacen/yahoo_finance/__init__.py
pybacen/yahoo_finance/regular_expressions.py
pybacen/yahoo_finance/request_param.py
pybacen/yahoo_finance/stocks.py
pybacen-1.1.3.dist-info/METADATA
pybacen-1.1.3.dist-info/WHEEL
pybacen-1.1.3.dist-info/top_level.txt
pybacen-1.1.3.dist-info/RECORD
