Metadata-Version: 2.1
Name: pybacen
Version: 1.1.3
Summary: Economic analysis in the Brazilian scenario
Home-page: UNKNOWN
Author: Rafael Pereira de Castro
Author-email: rafael.castro07@outlook.com
License: MIT
Keywords: bacen,pybacen,series bacen
Platform: UNKNOWN
Classifier: Development Status :: 3 - Alpha
Classifier: Intended Audience :: Developers
Classifier: Topic :: Software Development :: Build Tools
Classifier: License :: OSI Approved :: MIT License
Classifier: Programming Language :: Python :: 3
Classifier: Programming Language :: Python :: 3.6
Classifier: Programming Language :: Python :: 3.7
Classifier: Programming Language :: Python :: 3.8
Classifier: Programming Language :: Python :: 3.9
Classifier: Programming Language :: Python :: 3.10
Classifier: Programming Language :: Python :: 3 :: Only
Requires-Python: >=3.6, <4
Requires-Dist: pandas
Requires-Dist: numpy
Requires-Dist: aiohttp
Requires-Dist: nest-asyncio
Requires-Dist: plotly
